{
  "id": "palette-catalog",
  "name": "palette-catalog",
  "title": "Palette catalog: 15 palette datasets, swatches, index",
  "description": "Full palette data with verified HEX, reproducible swatch generation and index",
  "status": "completed",
  "dev_type": null,
  "scope": null,
  "package": null,
  "priority": "P2",
  "creator": "lyh",
  "assignee": "lyh",
  "createdAt": "2026-07-14",
  "completedAt": "2026-07-15",
  "branch": null,
  "base_branch": "dev",
  "worktree_path": null,
  "commit": null,
  "pr_url": null,
  "subtasks": [],
  "children": [],
  "parent": "07-14-palette-system",
  "relatedFiles": [],
  "notes": "",
  "meta": {}
}