{
  "id": "drawio-skill-changelog-upstream",
  "name": "drawio-skill-changelog-upstream",
  "title": "补录上游整合批到 skill 侧 base CHANGELOG",
  "description": "把上游整合批（配置/代码导入器、快照+漂移、AI图标目录、多页bundle、postprocess、raster、SysML/BPMN）补入 skills/drawio/CHANGELOG.md 的 Unreleased 段；不得扰动被 palette-skill-policy.test.js pin 的 ## 2.7.0 段；收尾跑 root npm test / just ci",
  "status": "completed",
  "dev_type": null,
  "scope": null,
  "package": null,
  "priority": "P3",
  "creator": "lyh",
  "assignee": "lyh",
  "createdAt": "2026-07-19",
  "completedAt": "2026-07-19",
  "branch": null,
  "base_branch": "dev",
  "worktree_path": null,
  "commit": null,
  "pr_url": null,
  "subtasks": [],
  "children": [],
  "parent": null,
  "relatedFiles": [],
  "notes": "",
  "meta": {}
}